calcrule_contribution_legacy/__init__.py
calcrule_contribution_legacy/admin.py
calcrule_contribution_legacy/apps.py
calcrule_contribution_legacy/calculation_rule.py
calcrule_contribution_legacy/config.py
calcrule_contribution_legacy/models.py
calcrule_contribution_legacy/signals.py
calcrule_contribution_legacy/tests.py
calcrule_contribution_legacy/urls.py
calcrule_contribution_legacy/views.py
calcrule_contribution_legacy/converters/__init__.py
calcrule_contribution_legacy/converters/contract_cpd_to_invoice_line_item.py
calcrule_contribution_legacy/converters/contract_to_invoice.py
calcrule_contribution_legacy/converters/policy_to_invoice.py
calcrule_contribution_legacy/converters/policy_to_line_item.py
calcrule_contribution_legacy/migrations/__init__.py
openimis_be_calcrule_contribution_legacy-1.9.0.dist-info/METADATA
openimis_be_calcrule_contribution_legacy-1.9.0.dist-info/WHEEL
openimis_be_calcrule_contribution_legacy-1.9.0.dist-info/top_level.txt
openimis_be_calcrule_contribution_legacy-1.9.0.dist-info/RECORD
