Metadata-Version: 2.4
Name: openimis-be-calcrule-contribution-legacy
Version: 1.9.0
Summary: The openIMIS Backend calculation rule contribution legacy reference module.
Home-page: https://openimis.org/
Author: Seweryn Niedzielski
Author-email: sniedzielski@soldevelo.com
License: GNU AGPL v3
Classifier: Environment :: Web Environment
Classifier: Framework :: Django
Classifier: Framework :: Django :: 2.1
Classifier: Intended Audience :: Developers
Classifier: License :: OSI Approved :: GNU Affero General Public License v3
Classifier: Operating System :: OS Independent
Classifier: Programming Language :: Python
Classifier: Programming Language :: Python :: 3.6
Classifier: Programming Language :: Python :: 3.7
Requires-Dist: django
Requires-Dist: django-db-signals
Requires-Dist: djangorestframework
Requires-Dist: openimis-be-core
Requires-Dist: openimis-be-policy
Requires-Dist: openimis-be-contract
Requires-Dist: openimis-be-calculation
Requires-Dist: openimis-be-invoice
Dynamic: author
Dynamic: author-email
Dynamic: classifier
Dynamic: description
Dynamic: description-content-type
Dynamic: home-page
Dynamic: license
Dynamic: requires-dist
Dynamic: summary
